tikapy/__init__.py
tikapy/api/__init__.py
tikapy-0.2.1.dist-info/WHEEL
tikapy-0.2.1.dist-info/RECORD
tikapy-0.2.1.dist-info/metadata.json
tikapy-0.2.1.dist-info/top_level.txt
tikapy-0.2.1.dist-info/DESCRIPTION.rst
tikapy-0.2.1.dist-info/METADATA
