Metadata-Version: 2.0
Name: tikapy
Version: 0.2.1
Summary: A python client for the MikroTik RouterOS API
Home-page: https://github.com/vshn/tikapy
Author: Andre Keller
Author-email: andre.keller@vshn.ch
License: BSD
Platform: UNKNOWN
Classifier: Development Status :: 3 - Alpha
Classifier: Intended Audience :: Developers
Classifier: Topic :: Software Development :: Build Tools
Classifier: License :: OSI Approved :: BSD License
Classifier: Programming Language :: Python :: 3
Classifier: Programming Language :: Python :: 3.4
